json2parquet/__init__.py
json2parquet/client.py
json2parquet/helpers.py
json2parquet-2.2.0.dist-info/LICENSE
json2parquet-2.2.0.dist-info/METADATA
json2parquet-2.2.0.dist-info/WHEEL
json2parquet-2.2.0.dist-info/top_level.txt
json2parquet-2.2.0.dist-info/RECORD
