Metadata-Version: 2.1
Name: json2parquet
Version: 2.2.0
Summary: 'A simple Parquet converter for JSON/python data'
Home-page: https://github.com/andrewgross/json2parquet
Author: Andrew Gross
Author-email: andrew.w.gross@gmail.com
Project-URL: Bug Tracker, https://github.com/andrewgross/json2parquet/issues
Classifier: Programming Language :: Python :: 3
Classifier: License :: OSI Approved :: MIT License
Classifier: Operating System :: OS Independent
Requires-Python: >=3.6
License-File: LICENSE
Requires-Dist: pyarrow
Requires-Dist: pandas
Requires-Dist: numpy >=1.14.0
Requires-Dist: ciso8601
